picklefield/__init__.py
picklefield/constants.py
picklefield/fields.py
django_picklefield-3.3.dist-info/LICENSE
django_picklefield-3.3.dist-info/METADATA
django_picklefield-3.3.dist-info/WHEEL
django_picklefield-3.3.dist-info/top_level.txt
django_picklefield-3.3.dist-info/RECORD
